advanced_selector/__init__.py
advanced_selector/colors.py
advanced_selector/keyboard.py
advanced_selector/menu.py
advanced_selector/wrapper.py
advanced_selector/xlib.py
advancedselector-3.1.0.dist-info/METADATA
advancedselector-3.1.0.dist-info/WHEEL
advancedselector-3.1.0.dist-info/top_level.txt
advancedselector-3.1.0.dist-info/RECORD
