Metadata-Version: 2.1
Name: advancedselector
Version: 3.1.0
Summary: Cross platform terminal selector implemented in Python
Author-email: kougen <info@kou-gen.net>
Maintainer-email: Joshua Hegedus <josh.hegedus@outlook.com>
Project-URL: Homepage, https://github.com/kougen/py-advanced-selector
Project-URL: Issues, https://github.com/kougen/py-advanced-selector/issues
Classifier: Programming Language :: Python :: 3
Classifier: License :: OSI Approved :: MIT License
Classifier: Operating System :: OS Independent
Requires-Python: >=3.8
Requires-Dist: getch ; os_name != "nt"
